MANIFEST.in
setup.py
ims_select2.egg-info/PKG-INFO
ims_select2.egg-info/SOURCES.txt
ims_select2.egg-info/dependency_links.txt
ims_select2.egg-info/top_level.txt
select2/__init__.py
select2/static/select2/select2-bootstrap.css
select2/static/select2/select2-spinner.gif
select2/static/select2/select2.css
select2/static/select2/select2.js
select2/static/select2/select2.png
select2/static/select2/select2_locale_ar.js
select2/static/select2/select2_locale_az.js
select2/static/select2/select2_locale_bg.js
select2/static/select2/select2_locale_ca.js
select2/static/select2/select2_locale_cs.js
select2/static/select2/select2_locale_da.js
select2/static/select2/select2_locale_de.js
select2/static/select2/select2_locale_el.js
select2/static/select2/select2_locale_en.js.template
select2/static/select2/select2_locale_es.js
select2/static/select2/select2_locale_et.js
select2/static/select2/select2_locale_eu.js
select2/static/select2/select2_locale_fa.js
select2/static/select2/select2_locale_fi.js
select2/static/select2/select2_locale_fr.js
select2/static/select2/select2_locale_gl.js
select2/static/select2/select2_locale_he.js
select2/static/select2/select2_locale_hr.js
select2/static/select2/select2_locale_hu.js
select2/static/select2/select2_locale_id.js
select2/static/select2/select2_locale_is.js
select2/static/select2/select2_locale_it.js
select2/static/select2/select2_locale_ja.js
select2/static/select2/select2_locale_ka.js
select2/static/select2/select2_locale_ko.js
select2/static/select2/select2_locale_lt.js
select2/static/select2/select2_locale_lv.js
select2/static/select2/select2_locale_mk.js
select2/static/select2/select2_locale_ms.js
select2/static/select2/select2_locale_nb.js
select2/static/select2/select2_locale_nl.js
select2/static/select2/select2_locale_pl.js
select2/static/select2/select2_locale_pt-BR.js
select2/static/select2/select2_locale_pt-PT.js
select2/static/select2/select2_locale_ro.js
select2/static/select2/select2_locale_rs.js
select2/static/select2/select2_locale_ru.js
select2/static/select2/select2_locale_sk.js
select2/static/select2/select2_locale_sv.js
