Metadata-Version: 1.1
Name: ims-select2
Version: 1.0.4
Summary: Installable Django app containing a 508-compliant version of select2.
Home-page: https://github.com/imsweb/django-select2
Author: Brad Rutten
Author-email: ruttenb@imsweb.com
License: MIT
Platform: UNKNOWN
Classifier: Development Status :: 5 - Production/Stable
Classifier: Intended Audience :: Developers
Classifier: License :: OSI Approved :: MIT License
Classifier: Operating System :: OS Independent
Classifier: Programming Language :: Python
Classifier: Topic :: Utilities
